hotelling/__init__.py
hotelling/cli.py
hotelling/helpers.py
hotelling/plots.py
hotelling/stats.py
hotelling-0.5.0.dist-info/AUTHORS.rst
hotelling-0.5.0.dist-info/LICENSE
hotelling-0.5.0.dist-info/METADATA
hotelling-0.5.0.dist-info/WHEEL
hotelling-0.5.0.dist-info/entry_points.txt
hotelling-0.5.0.dist-info/top_level.txt
hotelling-0.5.0.dist-info/RECORD
