Metadata-Version: 2.1
Name: hotelling
Version: 0.5.0
Summary: Hotelling implements one and two sample Hotelling T2 tests and control charts
Home-page: https://github.com/dionresearch/hotelling
Author: Francois Dion
Author-email: fdion@dionresearch.com
License: MIT license
Keywords: hotelling
Platform: UNKNOWN
Classifier: Development Status :: 4 - Beta
Classifier: Intended Audience :: Developers
Classifier: License :: OSI Approved :: MIT License
Classifier: Natural Language :: English
Classifier: Programming Language :: Python :: 3
Classifier: Programming Language :: Python :: 3.6
Classifier: Programming Language :: Python :: 3.7
Classifier: Programming Language :: Python :: 3.8
Classifier: Programming Language :: Python :: 3.9
Requires-Python: >=3.6
Requires-Dist: click
Requires-Dist: scipy
Requires-Dist: matplotlib
Requires-Dist: pandas
Requires-Dist: numpy
